IPS/__init__.py
IPS/asgi.py
IPS/settings.py
IPS/urls.py
IPS/wsgi.py
estimating/__init__.py
estimating/admin.py
estimating/apps.py
estimating/models.py
estimating/serializers.py
estimating/tests.py
estimating/views.py
estimating/migrations/__init__.py
hubplanner/__init__.py
hubplanner/admin.py
hubplanner/apps.py
hubplanner/hubplannerdata.py
hubplanner/models.py
hubplanner/tests.py
hubplanner/urls.py
hubplanner/views.py
hubplanner/migrations/__init__.py
logger/__init__.py
logger/admin.py
logger/apps.py
logger/logger.py
logger/models.py
logger/tests.py
logger/views.py
logger/migrations/__init__.py
salesforce/__init__.py
salesforce/admin.py
salesforce/apps.py
salesforce/models.py
salesforce/salesforce.py
salesforce/salesforceJWT.py
salesforce/salesforce_settings.py
salesforce/salesforce_trigger_handler.py
salesforce/salesforce_triggers.py
salesforce/tests.py
salesforce/urls.py
salesforce/views.py
salesforce/migrations/0001_initial.py
salesforce/migrations/0002_alter_salesforceoppportunity_description.py
salesforce/migrations/0003_alter_salesforceoppportunity_probability_and_more.py
salesforce/migrations/0004_alter_salesforceoppportunity_occurprobability_and_more.py
salesforce/migrations/0005_alter_salesforceoppportunity_customeraddress.py
salesforce/migrations/0006_alter_salesforceoppportunity_closedate_and_more.py
salesforce/migrations/0007_salesforceoppportunity_createddate_and_more.py
salesforce/migrations/0008_remove_salesforceoppportunity_updateddate_and_more.py
salesforce/migrations/0009_salesforceoppportunity_servicelevel1.py
salesforce/migrations/0010_salesforceoppportunity_salesforcecreateddate_and_more.py
salesforce/migrations/0011_account_attributes_billingaddress_recordtype_and_more.py
salesforce/migrations/__init__.py
workday/__init__.py
workday/admin.py
workday/apps.py
workday/models.py
workday/tests.py
workday/urls.py
workday/views.py
workday/migrations/__init__.py
IPSPROJECT_package-0.1.0.dist-info/METADATA
IPSPROJECT_package-0.1.0.dist-info/WHEEL
IPSPROJECT_package-0.1.0.dist-info/top_level.txt
IPSPROJECT_package-0.1.0.dist-info/RECORD
